yabox/__init__.py
yabox/version.py
yabox/algorithms/__init__.py
yabox/algorithms/base.py
yabox/algorithms/de.py
yabox/problems/__init__.py
yabox/problems/base.py
yabox-1.1.0.dist-info/LICENSE
yabox-1.1.0.dist-info/METADATA
yabox-1.1.0.dist-info/WHEEL
yabox-1.1.0.dist-info/top_level.txt
yabox-1.1.0.dist-info/RECORD
